polyhedral_analysis/__init__.py
polyhedral_analysis/atom.py
polyhedral_analysis/configuration.py
polyhedral_analysis/coordination_polyhedron.py
polyhedral_analysis/octahedral_analysis.py
polyhedral_analysis/orientation_parameters.py
polyhedral_analysis/polyhedra_recipe.py
polyhedral_analysis/polyhedron_trajectory.py
polyhedral_analysis/rotation_analyser.py
polyhedral_analysis/symmetry_measure.py
polyhedral_analysis/trajectory.py
polyhedral_analysis/utils.py
polyhedral_analysis-0.1.dist-info/LICENSE
polyhedral_analysis-0.1.dist-info/METADATA
polyhedral_analysis-0.1.dist-info/WHEEL
polyhedral_analysis-0.1.dist-info/top_level.txt
polyhedral_analysis-0.1.dist-info/RECORD
