Metadata-Version: 2.1
Name: polyhedral-analysis
Version: 0.1
Summary: A library for analysis of coordination polyhedra from molecular dynamics trajectories
Home-page: https://github.com/bjmorgan/polyhedral-analysis
Author: Benjamin J. Morgan
Author-email: bjm42@bath.ac.uk
License: MIT
Download-URL: https://github.com/bjmorgan/polyhedral-analysis/archive/0.1.tar.gz
Platform: UNKNOWN
Requires-Python: >=3.7
Requires-Dist: numpy
Requires-Dist: pymatgen
Requires-Dist: scipy
Requires-Dist: coverage (==4.3.4)
Requires-Dist: codeclimate-test-reporter
Requires-Dist: vg
Requires-Dist: monty
Requires-Dist: tqdm
Requires-Dist: typing-extensions
